probadg/Binomialdistribution.py
probadg/Gaussiandistribution.py
probadg/Generaldistribution.py
probadg/__init__.py
probadg/my_random.py
probadg-0.0.1.dist-info/METADATA
probadg-0.0.1.dist-info/WHEEL
probadg-0.0.1.dist-info/top_level.txt
probadg-0.0.1.dist-info/RECORD
