Metadata-Version: 2.1
Name: probadg
Version: 0.0.1
Summary: Binomial and Gaussian objects
Home-page: https://github.com/Alejandro-Duenas/probadg
Author: Alejandro Duenas Garcia
Author-email: alejandro19971231@gmail.com
License: UNKNOWN
Platform: UNKNOWN
Classifier: Programming Language :: Python :: 3
Classifier: License :: OSI Approved :: MIT License
Classifier: Operating System :: OS Independent
Requires-Python: >=3.6
